zoom_kurokesu/__init__.py
zoom_kurokesu/zoom_piloting.py
zoom_kurokesu-1.1.0.dist-info/METADATA
zoom_kurokesu-1.1.0.dist-info/WHEEL
zoom_kurokesu-1.1.0.dist-info/top_level.txt
zoom_kurokesu-1.1.0.dist-info/RECORD
