Metadata-Version: 2.1
Name: zoom-kurokesu
Version: 1.1.0
Summary: Python Package for controlling the zoom of Kurokesu's camera.
Home-page: https://github.com/pollen-robotics/zoom_kurokesu
Author: Pollen Robotics
Author-email: contact@pollen-robotics.com
License: UNKNOWN
Platform: UNKNOWN
Requires-Dist: pyserial
